Unit6/1/1.v
module binary_sub(output d , output b , input x , input y , input z);
	assign d = (~x&&~y&&z)||(~x&&y&&~z)||(x&&~y&&~z)||(x&&y&&z);
	assign b = (~x&&y)||(~x&&z)||(y&&z);
endmodule

Unit6/1/1_stimulus.v
`timescale 1ns / 1ps
module stimulus;
	reg x,y,z;
	wire b,d;
	binary_sub sub1(d,b,x,y,z);
	initial begin
		$dumpfile("output.vcd");
		$dumpvars(0,stimulus);
		x=0;
		y=0;
		z=0;
		#20 z = 1;
		#20 z = 0;
		y = 1;
		#20 z = 1;
		#20 x = 1;
		y = 0;
		z = 0;
		#20 z = 1;
		#20 z = 0;
		y = 1;
		#20 z = 1;
		#20 $finish;
		
	end
	initial begin 
		$display("time      x y z b d",$time);
		$monitor("%3d       %d %d %d %d %d",$time,x,y,z,b,d);
	end
endmodule

Unit6/1/output.vcd
$date
	Wed Jun 03 21:24:11 2020
$end
$version
	Icarus Verilog
$end
$timescale
	1ps
$end
$scope module stimulus $end
$var wire 1 ! d $end
$var wire 1 " b $end
$var reg 1 # x $end
$var reg 1 $ y $end
$var reg 1 % z $end
$scope module sub1 $end
$var wire 1 " b $end
$var wire 1 ! d $end
$var wire 1 # x $end
$var wire 1 $ y $end
$var wire 1 % z $end
$upscope $end
$upscope $end
$enddefinitions $end
#0
$dumpvars
0%
0$
0#
0"
0!
$end
#20000
1!
1"
1%
#40000
1$
0%
#60000
0!
1%
#80000
1!
0"
0%
0$
1#
#100000
0!
1%
#120000
0!
1$
0%
#140000
1!
1"
1%
