Unit6/3/3.v
module jk_ff(j,k,clr,clk,q,qbar);
	output q,qbar;
	input j,k,clk,clr;
	wire a,y,c,d,ybar,b,cbar;
	assign cbar = ~clk,
	a = ~(j&qbar&clk&clr),
	b = ~(k&clk&q),
	y = ~(a&ybar),
	ybar = ~(y&clr&b),
	c = ~(y&cbar),
	d = ~(cbar&ybar),
	q = ~(qbar&c),
	qbar = ~(q&clr&d);
endmodule

module counter(clr,clk,count_en,q);
	output [3:0] q;
	input clr,clk,count_en;
	wire c1,c2,c3;
	assign c1 = q[0]&count_en;
	assign c2 = q[1]&c1;
	assign c3 = q[2]&c2;
	jk_ff ff0(count_en,count_en,clr,clk,q[0],);
	jk_ff ff1(c1,c1,clr,clk,q[1],);
	jk_ff ff2(c2,c2,clr,clk,q[2],);
	jk_ff ff3(c3,c3,clr,clk,q[3],);
endmodule

Unit6/3/3_stimulus.v
`timescale 1ns/1ps
module stimulus;
	reg clk,clr,count_en;
	wire [3:0] q;
	initial 
		$monitor($time , "count q = %b , clr = %b , count_en = %b", q[3:0], clr , count_en);
	counter c1(clr,clk,count_en,q);
	
	initial begin
		$dumpfile("output.vcd");
		$dumpvars(0,stimulus);
		clr = 1'b0;
		#50 clr = 1'b1;
		#100 clr = 1'b0;
		#75 clr = 1'b1;
	end
	initial begin
		clk = 1'b0;
		forever #5 clk=~clk;
	end
	initial begin
		count_en=1'b0;
		#60 count_en=1'b1;
		#20 count_en=1'b0;
		#10 count_en=1'b1;
		
	end
	initial #500 $finish;
	
endmodule

Unit6/3/output.vcd
$date
	Fri Jun 05 16:47:39 2020
$end
$version
	Icarus Verilog
$end
$timescale
	1ps
$end
$scope module stimulus $end
$var wire 4 ! q [3:0] $end
$var reg 1 " clk $end
$var reg 1 # clr $end
$var reg 1 $ count_en $end
$scope module c1 $end
$var wire 1 % c1 $end
$var wire 1 & c2 $end
$var wire 1 ' c3 $end
$var wire 1 " clk $end
$var wire 1 # clr $end
$var wire 1 $ count_en $end
$var wire 4 ( q [3:0] $end
$scope module ff0 $end
$var wire 1 ) a $end
$var wire 1 * b $end
$var wire 1 + c $end
$var wire 1 , cbar $end
$var wire 1 " clk $end
$var wire 1 # clr $end
$var wire 1 - d $end
$var wire 1 $ j $end
$var wire 1 $ k $end
$var wire 1 . q $end
$var wire 1 / qbar $end
$var wire 1 0 y $end
$var wire 1 1 ybar $end
$upscope $end
$scope module ff1 $end
$var wire 1 2 a $end
$var wire 1 3 b $end
$var wire 1 4 c $end
$var wire 1 5 cbar $end
$var wire 1 " clk $end
$var wire 1 # clr $end
$var wire 1 6 d $end
$var wire 1 % j $end
$var wire 1 % k $end
$var wire 1 7 q $end
$var wire 1 8 qbar $end
$var wire 1 9 y $end
$var wire 1 : ybar $end
$upscope $end
$scope module ff2 $end
$var wire 1 ; a $end
$var wire 1 < b $end
$var wire 1 = c $end
$var wire 1 > cbar $end
$var wire 1 " clk $end
$var wire 1 # clr $end
$var wire 1 ? d $end
$var wire 1 & j $end
$var wire 1 & k $end
$var wire 1 @ q $end
$var wire 1 A qbar $end
$var wire 1 B y $end
$var wire 1 C ybar $end
$upscope $end
$scope module ff3 $end
$var wire 1 D a $end
$var wire 1 E b $end
$var wire 1 F c $end
$var wire 1 G cbar $end
$var wire 1 " clk $end
$var wire 1 # clr $end
$var wire 1 H d $end
$var wire 1 ' j $end
$var wire 1 ' k $end
$var wire 1 I q $end
$var wire 1 J qbar $end
$var wire 1 K y $end
$var wire 1 L ybar $end
$upscope $end
$upscope $end
$upscope $end
$enddefinitions $end
#0
$dumpvars
1L
0K
1J
0I
0H
1G
1F
1E
1D
1C
0B
1A
0@
0?
1>
1=
1<
1;
1:
09
18
07
06
15
14
13
12
11
00
1/
0.
0-
1,
1+
1*
1)
b0 (
0'
0&
0%
0$
0#
0"
b0 !
$end
#5000
1-
16
1?
1H
0,
05
0>
0G
1"
#10000
0-
06
0?
0H
1,
15
1>
1G
0"
#15000
1-
16
1?
1H
0,
05
0>
0G
1"
#20000
0-
06
0?
0H
1,
15
1>
1G
0"
#25000
1-
16
1?
1H
0,
05
0>
0G
1"
#30000
0-
06
0?
0H
1,
15
1>
1G
0"
#35000
1-
16
1?
1H
0,
05
0>
0G
1"
#40000
0-
06
0?
0H
1,
15
1>
1G
0"
#45000
1-
16
1?
1H
0,
05
0>
0G
1"
#50000
0-
06
0?
0H
1,
15
1>
1G
0"
1#
#55000
1-
16
1?
1H
0,
05
0>
0G
1"
#60000
0-
06
0?
0H
1,
15
1>
1G
0"
1$
#65000
01
10
1-
0)
16
1?
1H
0,
05
0>
0G
1"
#70000
0/
1%
b1 !
b1 (
1.
0+
1)
06
0?
0H
1,
15
1>
1G
0"
#75000
0:
00
11
19
1+
0*
16
02
1?
1H
0,
05
0>
0G
1"
#80000
08
0.
1/
b10 !
b10 (
17
0-
04
12
0?
0H
1*
1,
15
1>
1G
0%
0"
0$
#85000
1-
14
1?
1H
0,
05
0>
0G
1"
#90000
0-
04
0?
0H
1,
15
1>
1G
0"
1$
#95000
01
10
1-
0)
14
1?
1H
0,
05
0>
0G
1"
#100000
0/
1&
1%
b11 !
b11 (
1.
0+
1)
04
0?
0H
1,
15
1>
1G
0"
#105000
0C
00
09
11
1:
1B
1+
0*
14
03
1?
0;
1H
0,
05
0>
0G
1"
#110000
0%
0&
0A
0.
07
0'
1/
18
b100 !
b100 (
1@
0-
1*
06
13
0=
1;
0H
1,
15
1>
1G
0"
#115000
01
10
1-
0)
16
1=
1H
0,
05
0>
0G
1"
#120000
0/
1%
b101 !
b101 (
1.
0+
1)
06
0=
0H
1,
15
1>
1G
0"
#125000
0:
00
11
19
1+
0*
16
02
1=
1H
0,
05
0>
0G
1"
#130000
0%
08
0'
0.
0&
1/
b110 !
b110 (
17
0-
1*
04
12
0=
0H
1,
15
1>
1G
0"
#135000
01
10
1-
0)
14
1=
1H
0,
05
0>
0G
1"
#140000
1'
0/
1&
1%
b111 !
b111 (
1.
0+
1)
04
0=
0H
1,
15
1>
1G
0"
#145000
0L
00
09
0B
11
1:
1C
1K
1+
0*
14
03
1=
0<
1H
0D
0,
05
0>
0G
1"
#150000
0%
0&
0'
0I
0.
07
b0 !
b0 (
0@
0H
0K
0-
1*
06
13
0?
1<
1F
1/
18
1A
1L
1D
1,
15
1>
1G
0"
0#
#155000
1-
16
1?
1H
0,
05
0>
0G
1"
#160000
0-
06
0?
0H
1,
15
1>
1G
0"
#165000
1-
16
1?
1H
0,
05
0>
0G
1"
#170000
0-
06
0?
0H
1,
15
1>
1G
0"
#175000
1-
16
1?
1H
0,
05
0>
0G
1"
#180000
0-
06
0?
0H
1,
15
1>
1G
0"
#185000
1-
16
1?
1H
0,
05
0>
0G
1"
#190000
0-
06
0?
0H
1,
15
1>
1G
0"
#195000
1-
16
1?
1H
0,
05
0>
0G
1"
#200000
0-
06
0?
0H
1,
15
1>
1G
0"
#205000
1-
16
1?
1H
0,
05
0>
0G
1"
#210000
0-
06
0?
0H
1,
15
1>
1G
0"
#215000
1-
16
1?
1H
0,
05
0>
0G
1"
#220000
0-
06
0?
0H
1,
15
1>
1G
0"
#225000
01
10
1-
0)
16
1?
1H
0,
05
0>
0G
1"
1#
#230000
0/
1%
b1 !
b1 (
1.
0+
1)
06
0?
0H
1,
15
1>
1G
0"
#235000
0:
00
11
19
1+
0*
16
02
1?
1H
0,
05
0>
0G
1"
#240000
0%
08
0.
0&
1/
b10 !
b10 (
17
0-
1*
04
12
0?
0H
1,
15
1>
1G
0"
#245000
01
10
1-
0)
14
1?
1H
0,
05
0>
0G
1"
#250000
0/
1&
1%
b11 !
b11 (
1.
0+
1)
04
0?
0H
1,
15
1>
1G
0"
#255000
0C
00
09
11
1:
1B
1+
0*
14
03
1?
0;
1H
0,
05
0>
0G
1"
#260000
0%
0&
0A
0.
07
0'
1/
18
b100 !
b100 (
1@
0-
1*
06
13
0=
1;
0H
1,
15
1>
1G
0"
#265000
01
10
1-
0)
16
1=
1H
0,
05
0>
0G
1"
#270000
0/
1%
b101 !
b101 (
1.
0+
1)
06
0=
0H
1,
15
1>
1G
0"
#275000
0:
00
11
19
1+
0*
16
02
1=
1H
0,
05
0>
0G
1"
#280000
0%
08
0'
0.
0&
1/
b110 !
b110 (
17
0-
1*
04
12
0=
0H
1,
15
1>
1G
0"
#285000
01
10
1-
0)
14
1=
1H
0,
05
0>
0G
1"
#290000
1'
0/
1&
1%
b111 !
b111 (
1.
0+
1)
04
0=
0H
1,
15
1>
1G
0"
#295000
0L
00
09
0B
11
1:
1C
1K
1+
0*
14
03
1=
0<
1H
0D
0,
05
0>
0G
1"
#300000
0%
0&
0'
0J
0.
07
0@
1/
18
1A
b1000 !
b1000 (
1I
0-
1*
06
13
0?
1<
0F
1D
1,
15
1>
1G
0"
#305000
01
10
1-
0)
16
1?
1F
0,
05
0>
0G
1"
#310000
0/
1%
b1001 !
b1001 (
1.
0+
1)
06
0?
0F
1,
15
1>
1G
0"
#315000
0:
00
11
19
1+
0*
16
02
1?
1F
0,
05
0>
0G
1"
#320000
0%
08
0.
0&
1/
b1010 !
b1010 (
17
0-
1*
04
12
0?
0F
1,
15
1>
1G
0"
#325000
01
10
1-
0)
14
1?
1F
0,
05
0>
0G
1"
#330000
0/
1&
1%
b1011 !
b1011 (
1.
0+
1)
04
0?
0F
1,
15
1>
1G
0"
#335000
0C
00
09
11
1:
1B
1+
0*
14
03
1?
0;
1F
0,
05
0>
0G
1"
#340000
0%
0&
0A
0.
07
0'
1/
18
b1100 !
b1100 (
1@
0-
1*
06
13
0=
1;
0F
1,
15
1>
1G
0"
#345000
01
10
1-
0)
16
1=
1F
0,
05
0>
0G
1"
#350000
0/
1%
b1101 !
b1101 (
1.
0+
1)
06
0=
0F
1,
15
1>
1G
0"
#355000
0:
00
11
19
1+
0*
16
02
1=
1F
0,
05
0>
0G
1"
#360000
0%
08
0'
0.
0&
1/
b1110 !
b1110 (
17
0-
1*
04
12
0=
0F
1,
15
1>
1G
0"
#365000
01
10
1-
0)
14
1=
1F
0,
05
0>
0G
1"
#370000
1'
0/
1&
1%
b1111 !
b1111 (
1.
0+
1)
04
0=
0F
1,
15
1>
1G
0"
#375000
00
09
0B
0K
11
1:
1C
1L
1+
0*
14
03
1=
0<
1F
0E
0,
05
0>
0G
1"
#380000
0%
0&
0'
0.
07
0@
b0 !
b0 (
0I
1/
18
1A
1J
0-
1*
06
13
0?
1<
0H
1E
1,
15
1>
1G
0"
#385000
01
10
1-
0)
16
1?
1H
0,
05
0>
0G
1"
#390000
0/
1%
b1 !
b1 (
1.
0+
1)
06
0?
0H
1,
15
1>
1G
0"
#395000
0:
00
11
19
1+
0*
16
02
1?
1H
0,
05
0>
0G
1"
#400000
0%
08
0.
0&
1/
b10 !
b10 (
17
0-
1*
04
12
0?
0H
1,
15
1>
1G
0"
#405000
01
10
1-
0)
14
1?
1H
0,
05
0>
0G
1"
#410000
0/
1&
1%
b11 !
b11 (
1.
0+
1)
04
0?
0H
1,
15
1>
1G
0"
#415000
0C
00
09
11
1:
1B
1+
0*
14
03
1?
0;
1H
0,
05
0>
0G
1"
#420000
0%
0&
0A
0.
07
0'
1/
18
b100 !
b100 (
1@
0-
1*
06
13
0=
1;
0H
1,
15
1>
1G
0"
#425000
01
10
1-
0)
16
1=
1H
0,
05
0>
0G
1"
#430000
0/
1%
b101 !
b101 (
1.
0+
1)
06
0=
0H
1,
15
1>
1G
0"
#435000
0:
00
11
19
1+
0*
16
02
1=
1H
0,
05
0>
0G
1"
#440000
0%
08
0'
0.
0&
1/
b110 !
b110 (
17
0-
1*
04
12
0=
0H
1,
15
1>
1G
0"
#445000
01
10
1-
0)
14
1=
1H
0,
05
0>
0G
1"
#450000
1'
0/
1&
1%
b111 !
b111 (
1.
0+
1)
04
0=
0H
1,
15
1>
1G
0"
#455000
0L
00
09
0B
11
1:
1C
1K
1+
0*
14
03
1=
0<
1H
0D
0,
05
0>
0G
1"
#460000
0%
0&
0'
0J
0.
07
0@
1/
18
1A
b1000 !
b1000 (
1I
0-
1*
06
13
0?
1<
0F
1D
1,
15
1>
1G
0"
#465000
01
10
1-
0)
16
1?
1F
0,
05
0>
0G
1"
#470000
0/
1%
b1001 !
b1001 (
1.
0+
1)
06
0?
0F
1,
15
1>
1G
0"
#475000
0:
00
11
19
1+
0*
16
02
1?
1F
0,
05
0>
0G
1"
#480000
0%
08
0.
0&
1/
b1010 !
b1010 (
17
0-
1*
04
12
0?
0F
1,
15
1>
1G
0"
#485000
01
10
1-
0)
14
1?
1F
0,
05
0>
0G
1"
#490000
0/
1&
1%
b1011 !
b1011 (
1.
0+
1)
04
0?
0F
1,
15
1>
1G
0"
#495000
0C
00
09
11
1:
1B
1+
0*
14
03
1?
0;
1F
0,
05
0>
0G
1"
#500000
0%
0&
0A
0.
07
0'
1/
18
b1100 !
b1100 (
1@
0-
1*
06
13
0=
1;
0F
1,
15
1>
1G
0"
