Unit5/5/5.v
`timescale 1ns / 1ps
module mux(output z , input i0 , input i1 , input s);
	bufif0 #(1:2:3,3:4:5,5:6:7) gate1 (z, i0, s);
	bufif1 #(1:2:3,3:4:5,5:6:7) gate2 (z, i1, s);
endmodule

Unit5/5/5_stimulus.v
`timescale 1ns / 1ps
module stimulus;
	reg i0,i1,switch;
	wire out;
	mux mux1 (out , i0 , i1 , switch);
		
	initial begin
		$dumpfile("output.vcd");
		$dumpvars(0,stimulus);
		i0 = 0;
		i1 = 0;
		switch = 0;
		#20 i0 = 1;
		#20 switch = 1;
		#20 i1 = 1;
		#20 switch = 0;
		#20;
	end
	initial
		$monitor("time = %3d i0 = %d , i1 = %d , switch = %d , output = %d" , $time , i0 , i1 , switch , out);
endmodule

Unit5/5/output.vcd
$date
	Wed Jun 03 15:09:17 2020
$end
$version
	Icarus Verilog
$end
$timescale
	1ps
$end
$scope module stimulus $end
$var wire 1 ! out $end
$var reg 1 " i0 $end
$var reg 1 # i1 $end
$var reg 1 $ switch $end
$scope module mux1 $end
$var wire 1 " i0 $end
$var wire 1 # i1 $end
$var wire 1 $ s $end
$var wire 1 ! z $end
$upscope $end
$upscope $end
$enddefinitions $end
#0
$dumpvars
0$
0#
0"
x!
$end
#4000
0!
#20000
1"
#22000
1!
#40000
1$
#44000
x!
#46000
0!
#60000
1#
#62000
1!
#80000
0$
