Unit5/4/4.v
`timescale 1ns / 1ps
module rs_latch(output q , output qbar , input set , input reset);
	nor #(1)nor1(q , reset , qbar);
	nor #(1)nor2(qbar , set , q);
endmodule

Unit5/4/4_stimulus.v
`timescale 1ns / 1ps
module stimulus;
	reg set , reset;
	wire q , bar;
	rs_latch latch (q,qbar,set,reset);
	
	initial begin 
		$dumpfile("output.vcd");
		$dumpvars(0,stimulus);
		set=0;
		reset=0;
		#20 set = 0;
		reset =1;
		#20 set = 1;
		reset = 0;
		#20 set = 1;
		reset = 0;
		#20 set = 0;
		#20;
	end
	initial
		$monitor("time=%3d set=%d , reset=%d , q=%d , qbar=%d " ,$time , set,reset,q,qbar);
endmodule

Unit5/4/output.vcd
$date
	Wed Jun 03 14:35:47 2020
$end
$version
	Icarus Verilog
$end
$timescale
	1ps
$end
$scope module stimulus $end
$var wire 1 ! qbar $end
$var wire 1 " q $end
$var reg 1 # reset $end
$var reg 1 $ set $end
$scope module latch $end
$var wire 1 " q $end
$var wire 1 ! qbar $end
$var wire 1 # reset $end
$var wire 1 $ set $end
$upscope $end
$upscope $end
$enddefinitions $end
#0
$dumpvars
0$
0#
x"
x!
$end
#20000
1#
#21000
0"
#22000
1!
#40000
0#
1$
#41000
0!
#42000
1"
#80000
0$
