Unit7/7/7.v

//d flip flop with only changes at -ve edge of the clock 
module d_ff(q,clr,clk,d);
	output reg q;
	input clr,clk,d;
	always @(negedge clk) begin
		if(clr) 
			q <= 1'b0;
		else 
			q <= d;
	end
endmodule

Unit7/8/8_stimulus.v
`timescale 1ns/1ps
module stimulus;
	reg d,clk,clr;
	wire q;
	d_ff ff1(q,clr,clk,d);
	initial begin
		$dumpfile("output.vcd");
		$dumpvars(0,stimulus);
		#200 $finish;
	end
	initial begin
		clk = 1'b0;
		forever #5 clk = ~clk;
	end
	initial begin
		d = 1'b0;
		clr = 1'b0;
		#15 d = 1'b1;
		#20 d = 1'b0;
		#6 d = 1'b1;
		#10 clr = 1'b1;
		#23 clr = 1'b0;
	end
	initial 
		$monitor($time, " d = %d , q = %d clr = %d", d,q,clr);
endmodule

Unit7/7/output.vcd
$date
	Sat Jun 06 19:13:03 2020
$end
$version
	Icarus Verilog
$end
$timescale
	1ps
$end
$scope module stimulus $end
$var wire 1 ! q $end
$var reg 1 " clk $end
$var reg 1 # clr $end
$var reg 1 $ d $end
$scope module ff1 $end
$var wire 1 " clk $end
$var wire 1 # clr $end
$var wire 1 $ d $end
$var reg 1 ! q $end
$upscope $end
$upscope $end
$enddefinitions $end
#0
$dumpvars
0$
0#
0"
0!
$end
#5000
1"
#10000
0"
#15000
1"
1$
#20000
1!
0"
#25000
1"
#30000
0"
#35000
1"
0$
#40000
0!
0"
#41000
1$
#45000
1"
#50000
1!
0"
#51000
1#
#55000
1"
#60000
0!
0"
#65000
1"
#70000
0"
#74000
0#
#75000
1"
#80000
1!
0"
