Unit7/12/12.v
module ALU(out , select , a , b);
	output reg [4:0] out;
	input [2:0] select ;
	input [3:0] a , b;
	
	initial
		out = 5'b00000;
	always @(a or b or select) begin
		case(select)
			3'b000 : out = a;
			3'b001 : out = a+b;
			3'b010 : out = a-b;
			3'b011 : out = a/b;
			3'b100 : out = a%b;
			3'b101 : out = a<<1;
			3'b110 : out = a<<1;
			3'b111 : out = (a>b);
		endcase
	end
endmodule

Unit7/12/12_stimulus.v
`timescale 1ns/1ps

module stimulus;
	reg [3:0] a,b;
	reg [2:0] select;
	wire [4:0] out;
	ALU uut(out , select , a , b );
	initial begin
		$dumpfile("output.vcd");
		$dumpvars(0,stimulus);
		a = 4'b1010;
		b = 4'b1000;
		select = 3'b000;
		repeat(7)
			#20 select = select+1;
	end
	initial 
		$monitor($time , "  a = %d , b = %d , out = %d",a,b,out);
endmodule

Unit7/12/output.vcd
$date
	Mon Jun 08 21:10:56 2020
$end
$version
	Icarus Verilog
$end
$timescale
	1ps
$end
$scope module stimulus $end
$var wire 5 ! out [4:0] $end
$var reg 4 " a [3:0] $end
$var reg 4 # b [3:0] $end
$var reg 3 $ select [2:0] $end
$scope module uut $end
$var wire 4 % a [3:0] $end
$var wire 4 & b [3:0] $end
$var wire 3 ' select [2:0] $end
$var reg 5 ( out [4:0] $end
$upscope $end
$upscope $end
$enddefinitions $end
#0
$dumpvars
b1010 (
b0 '
b1000 &
b1010 %
b0 $
b1000 #
b1010 "
b1010 !
$end
#20000
b10010 !
b10010 (
b1 $
b1 '
#40000
b10 !
b10 (
b10 $
b10 '
#60000
b1 !
b1 (
b11 $
b11 '
#80000
b10 !
b10 (
b100 $
b100 '
#100000
b10100 !
b10100 (
b101 $
b101 '
#120000
b110 $
b110 '
#140000
b1 !
b1 (
b111 $
b111 '
